{
  "action_buttons": [
    {
      "text": "EXTRA TIME ACTIVATED",
      "cls": "button-1 action-button with-tip time-bank  suspended-action highlighted"
    },
    {
      "text": "BET 0.50",
      "cls": "button-1 action-button call with-tip call green "
    },
    {
      "text": "BET",
      "cls": "button-1 action-button with-tip raise green"
    },
    {
      "text": "CHECK",
      "cls": "button-1 action-button with-tip check green "
    },
    {
      "text": "FOLD",
      "cls": "button-1 action-button with-tip fold red "
    }
  ],
  "cards": [
    {
      "cls": "table-cards run-1",
      "text": "7\ns\n2\nd\nK\nc",
      "html": "<div class=\"table-cards run-1\"><div class=\"card-container card-s card-s-7 flipped big\"><div class=\"card-flipper card-flipper-animated\"><div "
    },
    {
      "cls": "card-container card-s  card-s-7 flipped big",
      "text": "7\ns",
      "html": "<div class=\"card-container card-s card-s-7 flipped big\"><div class=\"card-flipper card-flipper-animated\"><div class=\"front\"></div><div class="
    },
    {
      "cls": "card-flipper card-flipper-animated",
      "text": "7\ns",
      "html": "<div class=\"card-flipper card-flipper-animated\"><div class=\"front\"></div><div class=\"card\"><span class=\"value\" translate=\"no\">7</span><span "
    },
    {
      "cls": "card",
      "text": "7\ns",
      "html": "<div class=\"card\"><span class=\"value\" translate=\"no\">7</span><span class=\"suit sub-suit\" translate=\"no\">s</span><span class=\"suit\" translate"
    },
    {
      "cls": "card-container card-d  card-s-2 flipped big",
      "text": "2\nd",
      "html": "<div class=\"card-container card-d card-s-2 flipped big\"><div class=\"card-flipper card-flipper-animated\"><div class=\"front\"></div><div class="
    },
    {
      "cls": "card-flipper card-flipper-animated",
      "text": "2\nd",
      "html": "<div class=\"card-flipper card-flipper-animated\"><div class=\"front\"></div><div class=\"card\"><span class=\"value\" translate=\"no\">2</span><span "
    },
    {
      "cls": "card",
      "text": "2\nd",
      "html": "<div class=\"card\"><span class=\"value\" translate=\"no\">2</span><span class=\"suit sub-suit\" translate=\"no\">d</span><span class=\"suit\" translate"
    },
    {
      "cls": "card-container card-c  card-s-K flipped big",
      "text": "K\nc",
      "html": "<div class=\"card-container card-c card-s-K flipped big\"><div class=\"card-flipper card-flipper-animated\"><div class=\"front\"></div><div class="
    },
    {
      "cls": "card-flipper card-flipper-animated",
      "text": "K\nc",
      "html": "<div class=\"card-flipper card-flipper-animated\"><div class=\"front\"></div><div class=\"card\"><span class=\"value\" translate=\"no\">K</span><span "
    },
    {
      "cls": "card",
      "text": "K\nc",
      "html": "<div class=\"card\"><span class=\"value\" translate=\"no\">K</span><span class=\"suit sub-suit\" translate=\"no\">c</span><span class=\"suit\" translate"
    },
    {
      "cls": "table-player-cards  ",
      "text": "6\nd\n4\nh",
      "html": "<div class=\"table-player-cards \"><div class=\"card-container card-d card-s-6 flipped card-p1 med \"><div class=\"card-flipper card-flipper-anim"
    },
    {
      "cls": "card-container card-d  card-s-6 flipped card-p1   med ",
      "text": "6\nd",
      "html": "<div class=\"card-container card-d card-s-6 flipped card-p1 med \"><div class=\"card-flipper card-flipper-animated\"><div class=\"front\"></div><d"
    },
    {
      "cls": "card-flipper card-flipper-animated",
      "text": "6\nd",
      "html": "<div class=\"card-flipper card-flipper-animated\"><div class=\"front\"></div><div class=\"card\"><span class=\"value\" translate=\"no\">6</span><span "
    },
    {
      "cls": "card",
      "text": "6\nd",
      "html": "<div class=\"card\"><span class=\"value\" translate=\"no\">6</span><span class=\"suit sub-suit\" translate=\"no\">d</span><span class=\"suit\" translate"
    },
    {
      "cls": "card-container card-h  card-s-4 flipped card-p2   med ",
      "text": "4\nh",
      "html": "<div class=\"card-container card-h card-s-4 flipped card-p2 med \"><div class=\"card-flipper card-flipper-animated\"><div class=\"front\"></div><d"
    },
    {
      "cls": "card-flipper card-flipper-animated",
      "text": "4\nh",
      "html": "<div class=\"card-flipper card-flipper-animated\"><div class=\"front\"></div><div class=\"card\"><span class=\"value\" translate=\"no\">4</span><span "
    }
  ],
  "seated": [
    {
      "cls": "table-player table-player-1 decision-current  you-player ",
      "text": "Select\nHIGH CARD\n6\nd\n4\nh\nrobot\n\n48.00"
    },
    {
      "cls": "table-player table-player-7",
      "text": "vik\n\n48.00"
    }
  ],
  "bets": [],
  "dealers": [
    {
      "cls": "dealer-button-ctn dealer-position-7",
      "text": "",
      "html": "<div class=\"dealer-button-ctn dealer-position-7\"><div class=\"button \"></div></div>"
    }
  ],
  "inputs": [
    {
      "tag": "DIV",
      "cls": " entry-raise  entry-ctn",
      "type": ""
    },
    {
      "tag": "DIV",
      "cls": " entry-raise  entry-ctn",
      "type": ""
    },
    {
      "tag": "DIV",
      "cls": " entry-raise  entry-ctn",
      "type": ""
    },
    {
      "tag": "BUTTON",
      "cls": "button-1 action-button with-tip raise green",
      "type": "button"
    }
  ],
  "log": []
}